napari_cupy_image_processing/__init__.py
napari_cupy_image_processing/_cupy_image_processing.py
napari_cupy_image_processing/_function.py
napari_cupy_image_processing/_tests/__init__.py
napari_cupy_image_processing/_tests/test_function.py
napari_cupy_image_processing-0.4.1.dist-info/LICENSE
napari_cupy_image_processing-0.4.1.dist-info/METADATA
napari_cupy_image_processing-0.4.1.dist-info/WHEEL
napari_cupy_image_processing-0.4.1.dist-info/entry_points.txt
napari_cupy_image_processing-0.4.1.dist-info/top_level.txt
napari_cupy_image_processing-0.4.1.dist-info/RECORD
