Metadata-Version: 2.1
Name: napari-cupy-image-processing
Version: 0.4.1
Summary: GPU-accelerated image processing using CUDA
Home-page: https://github.com/haesleinhuepf/napari-cupy-image-processing
Author: Robert Haase
Author-email: robert.haase@tu-dresden.de
License: MIT
Project-URL: Bug Tracker, https://github.com/haesleinhuepf/napari-cupy-image-processing/issues
Project-URL: Documentation, https://github.com/haesleinhuepf/napari-cupy-image-processing#README.md
Project-URL: Source Code, https://github.com/haesleinhuepf/napari-cupy-image-processing
Project-URL: User Support, https://github.com/haesleinhuepf/napari-cupy-image-processing/issues
Classifier: Development Status :: 3 - Alpha
Classifier: Intended Audience :: Science/Research
Classifier: Framework :: napari
Classifier: Topic :: Scientific/Engineering :: Image Processing
Classifier: Topic :: Scientific/Engineering :: Information Analysis
Classifier: Programming Language :: Python
Classifier: Programming Language :: Python :: 3
Classifier: Programming Language :: Python :: 3.7
Classifier: Programming Language :: Python :: 3.8
Classifier: Programming Language :: Python :: 3.9
Classifier: Operating System :: OS Independent
Classifier: License :: OSI Approved :: MIT License
Requires-Python: >=3.7
License-File: LICENSE
Requires-Dist: napari-plugin-engine >=0.1.4
Requires-Dist: numpy
Requires-Dist: toolz
Requires-Dist: cupy
Requires-Dist: napari-tools-menu
Requires-Dist: scikit-image
Requires-Dist: napari-time-slicer >=0.4.8
Requires-Dist: napari-skimage-regionprops
Requires-Dist: napari-assistant
Requires-Dist: stackview >=0.3.2
